jpfund/__emaxis.py
jpfund/__fund_base.py
jpfund/__init__.py
jpfund/__morningstar.py
jpfund/__nikko.py
jpfund-0.0.1.dist-info/LICENSE
jpfund-0.0.1.dist-info/METADATA
jpfund-0.0.1.dist-info/WHEEL
jpfund-0.0.1.dist-info/top_level.txt
jpfund-0.0.1.dist-info/RECORD
