Metadata-Version: 2.1
Name: jpfund
Version: 0.0.1
Summary: Read prices of funds in Japan.
Home-page: https://github.com/kunigaku/jpfund
Author: kunigaku
Author-email: kunigaku@gmail.com
License: MIT
Keywords: pandas,fund
Platform: UNKNOWN
Classifier: Development Status :: 4 - Beta
Classifier: License :: OSI Approved :: MIT License
Classifier: Programming Language :: Python
Classifier: Programming Language :: Python :: 3
Classifier: Programming Language :: Python :: 3.4
Classifier: Programming Language :: Python :: 3.5
Classifier: Programming Language :: Python :: 3.6
Classifier: Programming Language :: Python :: 3.7
Requires-Dist: pandas
Requires-Dist: requests
Requires-Dist: pyquery
